setup.py
mlaws_distributions/Binomialdistribution.py
mlaws_distributions/Gaussiandistribution.py
mlaws_distributions/Generaldistribution.py
mlaws_distributions/__init__.py
mlaws_distributions.egg-info/PKG-INFO
mlaws_distributions.egg-info/SOURCES.txt
mlaws_distributions.egg-info/dependency_links.txt
mlaws_distributions.egg-info/not-zip-safe
mlaws_distributions.egg-info/top_level.txt