Metadata-Version: 1.0
Name: mlaws-distributions
Version: 0.1
Summary: Gaussian & Binomial distributions
Home-page: UNKNOWN
Author: Mohamed Zeglam
Author-email: UNKNOWN
License: UNKNOWN
Platform: UNKNOWN
